feature_selector_classif/__init__.py
feature_selector_classif/combinator.py
feature_selector_classif/rfa.py
feature_selector_classif/selector.py
feature_selector_classif/utils.py
feature_selector_banking-0.2.0.dist-info/METADATA
feature_selector_banking-0.2.0.dist-info/WHEEL
feature_selector_banking-0.2.0.dist-info/top_level.txt
feature_selector_banking-0.2.0.dist-info/RECORD
