Metadata-Version: 2.4
Name: feature-selector-banking
Version: 0.2.0
Summary: Selecting features using best metrics 
Author-email: Amir <zakirovskiy116@gmail.com>
License: MIT
Project-URL: Homepage, https://github.com/LinearSpace07/feature-selector
Project-URL: Repository, https://github.com/LinearSpace07/feature-selector
Classifier: License :: OSI Approved :: MIT License
Classifier: Programming Language :: Python
Classifier: Programming Language :: Python :: 3
Requires-Python: >=3.8
Provides-Extra: dev
Requires-Dist: pytest; extra == "dev"
Requires-Dist: black; extra == "dev"
